discord_menu_core/__init__.py
discord_menu_core/smart.py
discord_menu_core/version.py
th_menu/__init__.py
th_menu/actions.py
th_menu/loader.py
th_menu/localization.py
th_menu/paginator.py
th_menu/search.py
th_menu/smart.py
th_menu/version.py
TH_Menu-0.2.3.dist-info/LICENSE.txt
TH_Menu-0.2.3.dist-info/METADATA
TH_Menu-0.2.3.dist-info/WHEEL
TH_Menu-0.2.3.dist-info/top_level.txt
TH_Menu-0.2.3.dist-info/RECORD
