Metadata-Version: 2.1
Name: TH-Menu
Version: 0.2.3
Summary: Умная система вложенных меню с кнопкой 'Назад' для nextcord
Home-page: https://github.com/Thomson-Hate/TH-Menu/blob/main/README.md
Author: Ivan (Thomson Hate)
Classifier: Programming Language :: Python :: 3
Classifier: License :: OSI Approved :: MIT License
Classifier: Framework :: AsyncIO
Classifier: Topic :: Software Development :: Libraries
Requires-Python: >=3.8
License-File: LICENSE.txt
Requires-Dist: nextcord>=2.5.0
Requires-Dist: requests>=2.0.0
